smart_fixtures/__init__.py
smart_fixtures/apps.py
smart_fixtures/management/__init__.py
smart_fixtures/management/commands/__init__.py
smart_fixtures/management/commands/loaddata.py
smart_fixtures/tests/__init__.py
smart_fixtures/tests/test_create_copied_files_message.py
smart_fixtures/tests/test_loaddata_command.py
smart_fixtures/utils.py
django_smart_fixtures-2.0.4.dist-info/LICENSE
django_smart_fixtures-2.0.4.dist-info/METADATA
django_smart_fixtures-2.0.4.dist-info/WHEEL
django_smart_fixtures-2.0.4.dist-info/RECORD
