Metadata-Version: 2.1
Name: django-smart-fixtures
Version: 2.0.4
Summary: Don't be stupid, and load fixtures in a smart way
Home-page: https://github.com/roknicmilos/django-smart-fixtures
License: MIT
Keywords: fixtures,loaddata,load fixtures,smart fixtures
Author: Miloš Roknić
Author-email: roknic.milos.994@gmail.com
Requires-Python: >=3.10,<4.0
Classifier: Environment :: Web Environment
Classifier: Framework :: Django
Classifier: Framework :: Django :: 4.0
Classifier: Framework :: Django :: 5.0
Classifier: Intended Audience :: Developers
Classifier: License :: OSI Approved :: MIT License
Classifier: Operating System :: OS Independent
Classifier: Programming Language :: Python :: 3
Classifier: Programming Language :: Python :: 3.10
Classifier: Programming Language :: Python :: 3.11
Classifier: Programming Language :: Python :: 3.12
Classifier: Topic :: Software Development :: Libraries :: Application Frameworks
Classifier: Topic :: Software Development :: Libraries :: Python Modules
Requires-Dist: Django (>=4.0,<6.0)
Requires-Dist: pillow (>=11.0.0,<12.0.0)
Requires-Dist: pyyaml (>=6.0.2,<7.0.0)
Project-URL: Documentation, https://github.com/roknicmilos/django-smart-fixtures/blob/main/README.md
Project-URL: Repository, https://github.com/roknicmilos/django-smart-fixtures
